astrolabe/__init__.py
astrolabe/api.py
astrolabe/error.py
astrolabe/utils.py
astrolabe_sdk-1.0.2.dist-info/licenses/LICENSE
astrolabe_sdk-1.0.2.dist-info/WHEEL
astrolabe_sdk-1.0.2.dist-info/METADATA
astrolabe_sdk-1.0.2.dist-info/RECORD
