Metadata-Version: 2.4
Name: astrolabe-sdk
Version: 1.0.2
Summary: Python SDK for the OKAPI:Astrolabe API
Keywords: space,space debris,astrolabe,space traffic coordination,okapi orbits,sdk,REST API
Author-email: "OKAPI:Orbits" <contact@okapiorbits.space>
Requires-Python: >= 3.10
Classifier: Development Status :: 5 - Production/Stable
Classifier: Programming Language :: Python :: 3
Classifier: Programming Language :: Python :: 3.10
Classifier: Programming Language :: Python :: 3.11
Classifier: Programming Language :: Python :: 3.12
Classifier: Programming Language :: Python :: 3.13
Classifier: License :: OSI Approved :: MIT License
Classifier: Intended Audience :: Developers
Classifier: Topic :: Utilities
License-File: LICENSE
Requires-Dist: python-dotenv
Requires-Dist: requests
Requires-Dist: ruff ; extra == "dev"
Requires-Dist: mypy ; extra == "dev"
Requires-Dist: types-requests ; extra == "dev"
Requires-Dist: pytest ; extra == "dev"
Requires-Dist: pytest-cov ; extra == "dev"
Requires-Dist: pytest-env ; extra == "dev"
Requires-Dist: pytest-html ; extra == "dev"
Requires-Dist: coverage[toml] ; extra == "dev"
Requires-Dist: pytest-xdist ; extra == "dev"
Requires-Dist: coverage-badge ; extra == "dev"
Requires-Dist: sphinx ; extra == "docs"
Requires-Dist: sphinx-book-theme ; extra == "docs"
Requires-Dist: myst-parser ; extra == "docs"
Requires-Dist: sphinx-autoapi ; extra == "docs"
Requires-Dist: sphinx-click ; extra == "docs"
Requires-Dist: myst-nb ; extra == "docs"
Project-URL: Homepage, https://www.okapiorbits.space
Provides-Extra: dev
Provides-Extra: docs
